e4s_alc/__init__.py
e4s_alc/cli/__init__.py
e4s_alc/cli/__main__.py
e4s_alc/cli/cli_view.py
e4s_alc/cli/command.py
e4s_alc/cli/entry.py
e4s_alc/cli/commands/__init__.py
e4s_alc/cli/commands/add.py
e4s_alc/cli/commands/create.py
e4s_alc/cli/commands/init.py
e4s_alc/model/__init__.py
e4s_alc/model/add.py
e4s_alc/model/create.py
e4s_alc/model/init.py
e4s_alc/model/container/__init__.py
e4s_alc/model/container/docker.py
e4s_alc/model/container/podman.py
e4s_alc/mvc/__init__.py
e4s_alc/mvc/controller.py
e4s_alc/mvc/model.py
e4s_alc-0.1.1.dist-info/LICENSE
e4s_alc-0.1.1.dist-info/METADATA
e4s_alc-0.1.1.dist-info/WHEEL
e4s_alc-0.1.1.dist-info/entry_points.txt
e4s_alc-0.1.1.dist-info/top_level.txt
e4s_alc-0.1.1.dist-info/RECORD
