Metadata-Version: 2.1
Name: e4s-alc
Version: 0.1.1
Summary: Build docker containers quickly with Spack integration.
License-File: LICENSE
Requires-Dist: docker
Requires-Dist: podman
